setup.cfg
setup.py
MyUselessLib/__init__.py
MyUselessLib/mod1.py
MyUselessLib/mod2.py
MyUselessLib/mod3.py
MyUselessLib.egg-info/PKG-INFO
MyUselessLib.egg-info/SOURCES.txt
MyUselessLib.egg-info/dependency_links.txt
MyUselessLib.egg-info/not-zip-safe
MyUselessLib.egg-info/top_level.txt