Metadata-Version: 1.0
Name: MyUselessLib
Version: 0.1
Summary: I don`t know why i created THIS
Home-page: UNKNOWN
Author: UNKNOWN
Author-email: sanya14000@ukr.net
License: UNKNOWN
Platform: UNKNOWN
